c400g_ptz/__init__.py
c400g_ptz/_version.py
c400g_ptz/ptz.py
c400g_ptz-0.1.2.dist-info/METADATA
c400g_ptz-0.1.2.dist-info/WHEEL
c400g_ptz-0.1.2.dist-info/licenses/LICENSE
c400g_ptz-0.1.2.dist-info/RECORD
