Metadata-Version: 2.4
Name: c400g-ptz
Version: 0.1.2
Summary: ipTIME C400G ONVIF PTZ control wrapper
Project-URL: Homepage, https://github.com/wonjj6768/c400g-ptz
Project-URL: Repository, https://github.com/wonjj6768/c400g-ptz
Author-email: wonjj6768 <wonjj6768@gmail.com>
License: MIT
License-File: LICENSE
Keywords: c400g,camera,ipcam,iptime,onvif,ptz
Classifier: Development Status :: 4 - Beta
Classifier: Intended Audience :: Developers
Classifier: License :: OSI Approved :: MIT License
Classifier: Operating System :: OS Independent
Classifier: Programming Language :: Python :: 3
Classifier: Programming Language :: Python :: 3.9
Classifier: Programming Language :: Python :: 3.10
Classifier: Programming Language :: Python :: 3.11
Classifier: Programming Language :: Python :: 3.12
Classifier: Topic :: Home Automation
Classifier: Topic :: Multimedia :: Video
Requires-Python: >=3.9
Requires-Dist: onvif-zeep>=0.2.12
